{
  "General": {
    "EncodedBinFiles": "File binari criptati",
    "SelectFile": "Selezionare un file",
    "SaveFile": "Salvataggio di un file",
    "PressEnterToSelectFile": "Premere [Invio] per selezionare un file...",
    "YouSelectedFile": "Avete selezionato questo file : %s\n\n",
    "EnterPassword": "Inserire la password : ",
    "PressEnterToSaveFile": "Premere [Invio] per salvare il file...",
    "AllFiles": "Tutti i file"
  },
  "CommonThings": {
    "NoGUI": "Non è stata rilevata alcuna interfaccia grafica. Inserite il percorso assoluto del vostro file : ",
    "EchoedAttempt": "Tentativo fallito : %s\n",
    "ToManyEchoedAttempts": "Troppi tentativi falliti",
    "Hour": "ora",
    "Hours": "ore",
    "Minute": "minuto",
    "Minutes": "minuti",
    "Second": "secondo",
    "Seconds": "secondi",
    "Time": "%d %s, %02d %s e %02d,%06d %s"
  },
  "Intro": {
    "WhatWouldYouLikeToDo": "Cosa ti piacerebbe fare?\n - Codifica di un file (c)\n - Decodifica di un file (d)\n - Leggi la licenza (l)\n",
    "EncodeInitial": "c",
    "DecodeInitial": "d",
    "LicenseInitial": "l"
  },
  "Encoding": {
    "YesInitial": "s",
    "NoInitial": "n",
    "IsPwdOk": "Siete soddisfatti di questo?",
    "CrackedIn": "La password verrebbe decifrata in %s\n",
    "MoreThan290": "più di 90 anni.",
    "PasswordValidated": "La password è stata convalidata.",
    "FileEncodedIn": "File codificato in %s.\n",
    "WhichEncodingMethod": "Quale metodo di crittografia si desidera utilizzare?\n - Solo crittografia XOR (x)\n - Crittografia XOR e rotativa (consigliata) (xr)\n"
  },
  "Decoding": {
    "FileDecodedIn": "File decodificato in %s.\n"
  }
}
